colored_custom_logger/__init__.py
colored_custom_logger-1.6.1.dist-info/METADATA
colored_custom_logger-1.6.1.dist-info/WHEEL
colored_custom_logger-1.6.1.dist-info/licenses/LICENSE
colored_custom_logger-1.6.1.dist-info/RECORD
