Metadata-Version: 2.4
Name: colored_custom_logger
Version: 1.6.1
Summary: A custom logger with colorful output
Project-URL: Homepage, https://github.com/robin-collins/colored_custom_logger
Project-URL: Bug Tracker, https://github.com/robin-collins/colored_custom_logger/issues
Project-URL: Documentation, https://robin-collins.github.io/colored_custom_logger/
Author-email: Robin Collins <robin@blackcat-it.com.au>
License: MIT License
License-File: LICENSE
Classifier: Intended Audience :: Developers
Classifier: License :: OSI Approved :: MIT License
Classifier: Operating System :: OS Independent
Classifier: Programming Language :: Python :: 3
Classifier: Programming Language :: Python :: 3.7
Classifier: Programming Language :: Python :: 3.8
Classifier: Programming Language :: Python :: 3.9
Classifier: Programming Language :: Python :: 3.10
Classifier: Programming Language :: Python :: 3.11
Classifier: Topic :: System :: Logging
Requires-Python: >=3.7
Requires-Dist: colorama
